astro_test_package/__init__.py
astro_test_package/astro_analyzer.py
astro_test_package-0.0.2.dist-info/LICENSE
astro_test_package-0.0.2.dist-info/METADATA
astro_test_package-0.0.2.dist-info/WHEEL
astro_test_package-0.0.2.dist-info/top_level.txt
astro_test_package-0.0.2.dist-info/RECORD
