Metadata-Version: 2.1
Name: astro_test_package
Version: 0.0.2
Summary: Astro test package
Author-email: Mikhail Krivonosov <mike_live@mail.ru>
Project-URL: Homepage, https://github.com/mike-live/astro-test-package
Project-URL: Issues, https://github.com/mike-live/astro-test-package/issues
Classifier: Programming Language :: Python :: 3
Requires-Python: >=3.8
License-File: LICENSE
Requires-Dist: opencv-python >4
